{
  "id": "pohyb-vyfuk-prumerna-rychlost",
  "subtopicId": "rychlost",
  "topicId": "pohyb",
  "title": "Průměrná rychlost dopravního prostředku (Výfuk)",
  "description": "Žáci změří průměrnou rychlost libovolného dopravního prostředku ve svém okolí – auto, eskalátor, kůň nebo cokoli jiného. Vypočítají poměr celkové vzdálenosti a doby jízdy, výsledek porovnají s rychlostí z dopravního značení a zdůvodní případné rozdíly. Korespondenční domácí projekt s protokolem; zadání z korespondenčního semináře Výfuk přímo cíleného na 6. a 7. třídu ZŠ.",
  "source": {
    "label": "Výfuk – 11. ročník, 6. série",
    "url": "https://vyfuk.org/ulohy/r11/s6"
  }
}
