{
  "id": "astronomie-astrocz-plutoidy",
  "subtopicId": "dalsi-vesmirna-telesa",
  "topicId": "astronomie",
  "title": "Astro.cz: Plutoidy — proč Pluto není planeta",
  "type": "link",
  "description": "Článek vysvětlující vznik kategorie plutoidy a překlasifikování Pluta: rozhodnutí IAU z roku 2006, definice trpasličí planety a nová kategorie plutoidy (trpasličí planety za Neptunem, včetně Eris). Aktuální a faktograficky přesné vysvětlení, proč Pluto přestalo být planetou.",
  "url": "https://www.astro.cz/clanky/slunecni-soustava/plutoidy-aneb-nova-kategorie-ve-slunecni-soustave.html"
}
