{
  "id": "eo-multimetr-dumy-pristroje",
  "subtopicId": "multimetr",
  "topicId": "elektricke-obvody",
  "title": "DUMy.cz: Elektrické měřicí přístroje — analogové (pracovní list)",
  "type": "worksheet",
  "description": "Pracovní list z portálu DUMy.cz věnovaný analogovým elektrickým měřicím přístrojům. Žáci se učí číst stupnici a pochopit principy měření voltmetrem a ampérmetrem — tedy základ porozumění multimetru. Přístup vyžaduje bezplatnou registraci na portálu DUMy.cz.",
  "url": "https://www.dumy.cz/material/117375-elektricke-merici-pristroje-analogove-merici-pristroje-pracovni-list"
}
