{
  "id": "mereni-teplota-svetenergie-balonek",
  "subtopicId": "teplota",
  "topicId": "mereni",
  "title": "Vím proč: Balónek na lahvi a teplota (Svět energie)",
  "type": "video",
  "description": "Krátké video ze série Vím proč (Svět energie / ČEZ): balónek nasazený na plastovou láhev se při zahřátí nafukuje a při ochlazení splaskuje — přehledná demonstrace vlivu teploty na objem plynu. Video pochází ze žákovské soutěže a pokus lze snadno zopakovat ve třídě.",
  "url": "https://www.svetenergie.cz/cz/vim-proc/video/2396"
}
