{
  "id": "sila-a-jeji-znazorneni",
  "topicId": "sila",
  "name": "Síla a její znázornění",
  "order": 1,
  "notebookEntry": {
    "latex": "\\documentclass[10pt]{article}\n\\usepackage[utf8]{inputenc}\n\\usepackage[T1]{fontenc}\n\\usepackage[czech]{babel}\n\\usepackage{geometry}\n\\usepackage[table]{xcolor}\n\\usepackage{tcolorbox}\n\\usepackage{amsmath,amssymb}\n\\usepackage{tikz}\n\\usetikzlibrary{calc,arrows.meta,decorations.pathmorphing,patterns}\n\\usepackage{enumitem}\n\n\\geometry{a4paper, margin=2cm}\n\n\\definecolor{zfblue}{HTML}{2A6DAB}\n\\definecolor{zfpurple}{HTML}{6A3AA0}\n\\definecolor{zfred}{HTML}{B54530}\n\\definecolor{zfgreen}{HTML}{2A8A4C}\n\\definecolor{zfgray}{HTML}{FAFAFA}\n\n\\setlist[itemize]{noitemsep, topsep=2pt, leftmargin=18pt}\n\n\\begin{document}\n\\pagestyle{empty}\n\n\\begin{flushleft}\n\n{\\LARGE \\bfseries Síla a její znázornění} \\\\[2mm]\n{\\color{zfblue}\\hrule height 1.5pt}\n\\vspace{4mm}\n\n\\begin{itemize}\n    \\item \\textbf{Síla} popisuje, jak na sebe tělesa působí.\n    \\item Značka: \\textbf{F} (z anglického \\emph{force}). Jednotka: \\textbf{newton (N)}.\n    \\item Síla může těleso \\textbf{zrychlit, zpomalit, deformovat} nebo změnit směr pohybu.\n\\end{itemize}\n\n\\vspace{4mm}\n{\\Large \\bfseries \\color{zfblue} Účinky síly}\n\\vspace{2mm}\n\n\\begin{center}\n\\renewcommand{\\arraystretch}{1.3}\n\\setlength{\\tabcolsep}{8pt}\n\\begin{tabular}{|l|l|}\n\\hline\n\\rowcolor{zfblue!25}\n\\bfseries Účinek & \\bfseries Příklad \\\\\n\\hline\nuvedení do pohybu & kopnutí do míče \\\\\nzastavení & zachycení míče \\\\\nzměna směru & odraz míče od stěny \\\\\ndeformace (změna tvaru) & stlačení pružiny, pomačkání plastu \\\\\n\\hline\n\\end{tabular}\n\\end{center}\n\n\\vspace{4mm}\n{\\Large \\bfseries \\color{zfblue} Síla má tři vlastnosti}\n\\vspace{2mm}\n\n\\begin{tcolorbox}[colback=zfgray, colframe=zfblue!50, boxrule=0.5pt, arc=2pt, left=6pt, right=6pt, top=4pt, bottom=4pt]\n\\begin{enumerate}[noitemsep, topsep=2pt, leftmargin=18pt]\n    \\item \\textbf{Velikost} -- udává se v newtonech (N).\n    \\item \\textbf{Směr} -- kam síla působí.\n    \\item \\textbf{Působiště} -- bod, ve kterém na těleso působí.\n\\end{enumerate}\n\\end{tcolorbox}\n\n\\vspace{3mm}\n{\\Large \\bfseries \\color{zfblue} Znázornění síly orientovanou úsečkou}\n\\vspace{2mm}\n\n\\begin{center}\n\\begin{tikzpicture}[scale=1, every node/.style={font=\\small}]\n    % Bedna\n    \\draw[thick, fill=gray!30] (0, 0) rectangle (2, 1.5);\n\n    % Šipka síly\n    \\draw[->, ultra thick, zfred] (1, 0.75) -- (4.5, 0.75);\n    \\node[font=\\bfseries, color=zfred] at (3, 1.1) {$F = 50$ N};\n\n    % Působiště\n    \\fill[zfred] (1, 0.75) circle (0.1);\n    \\node[font=\\small, anchor=east] at (1, 0.4) {působiště};\n\n    % Šipka = směr\n    \\node[font=\\small] at (5.5, 0.75) {směr};\n\n    % Délka = velikost\n    \\draw[thick, dashed, gray] (1, -0.3) -- (4.5, -0.3);\n    \\node[font=\\small, gray!50!black] at (2.75, -0.6) {délka šipky = velikost};\n\\end{tikzpicture}\n\\end{center}\n\n\\vspace{2mm}\n\\begin{itemize}\n    \\item Sílu kreslíme jako \\textbf{šipku}.\n    \\item \\textbf{Začátek} šipky = působiště. \\textbf{Směr} šipky = směr síly. \\textbf{Délka} šipky = velikost síly (podle zvoleného měřítka).\n\\end{itemize}\n\n\\vspace{4mm}\n{\\Large \\bfseries \\color{zfblue} Druhy sil}\n\\vspace{2mm}\n\n\\begin{itemize}\n    \\item \\textbf{Tíhová síla} -- působí Země na každé těleso, směr svisle dolů.\n    \\item \\textbf{Tlaková a tahová síla} -- tlačíme nebo táhneme předmět.\n    \\item \\textbf{Třecí síla} -- brání pohybu po povrchu.\n    \\item \\textbf{Pružná síla} -- pružina vrací svůj tvar.\n    \\item \\textbf{Magnetická síla, elektrická síla} -- působí na dálku.\n\\end{itemize}\n\n\\vspace{3mm}\n{\\Large \\bfseries \\color{zfblue} Příklady velikostí sil}\n\\vspace{2mm}\n\n\\begin{itemize}\n    \\item Zvedne 100 g (jablko): asi 1 N.\n    \\item Zvedne 1 kg (knihu): asi 10 N.\n    \\item Zvedne žáka (40 kg): asi 400 N.\n    \\item Auto, které tlačíme po rovině: 200--500 N.\n\\end{itemize}\n\n\\end{flushleft}\n\\end{document}\n"
  }
}
